iplooker/.gitignore
iplooker/__init__.py
iplooker/api_key_manager.py
iplooker/encoded_keys.json
iplooker/ip_formatter.py
iplooker/ip_looker.py
iplooker/lookup_result.py
iplooker/lookup_source.py
iplooker/sources/__init__.py
iplooker/sources/ip_api_com.py
iplooker/sources/ipapi_co.py
iplooker/sources/ipapi_is.py
iplooker/sources/ipdata_co.py
iplooker/sources/ipgeolocation_io.py
iplooker/sources/ipinfo_io.py
iplooker/sources/iplocate_io.py
iplooker/sources/ipregistry_co.py
iplooker-0.5.1.dist-info/METADATA
iplooker-0.5.1.dist-info/WHEEL
iplooker-0.5.1.dist-info/entry_points.txt
iplooker-0.5.1.dist-info/licenses/LICENSE
iplooker-0.5.1.dist-info/RECORD
