Metadata-Version: 2.4
Name: iplooker
Version: 0.5.1
Summary: Look up location, ISP, and more about an IP address from multiple sources
License-Expression: MIT
License-File: LICENSE
Author: Danny Stewart
Author-email: danny@stewart.cc
Requires-Python: >=3.12,<4.0
Classifier: Development Status :: 5 - Production/Stable
Classifier: Intended Audience :: Developers
Classifier: Intended Audience :: End Users/Desktop
Classifier: Intended Audience :: Information Technology
Classifier: Intended Audience :: System Administrators
Classifier: License :: OSI Approved :: MIT License
Classifier: Programming Language :: Python :: 3
Classifier: Programming Language :: Python :: 3.12
Classifier: Programming Language :: Python :: 3.13
Classifier: Topic :: Software Development :: Libraries
Classifier: Topic :: Software Development :: Libraries :: Python Modules
Classifier: Topic :: System :: Networking
Classifier: Topic :: Utilities
Requires-Dist: polykit (>=0.14.6)
Requires-Dist: pycountry (>=24.6.1,<25.0.0)
Requires-Dist: requests (>=2.32.5,<3.0.0)
Project-URL: Repository, https://github.com/dannystewart/iplooker
